gym_aloha/__init__.py
gym_aloha/constants.py
gym_aloha/constants_dummy.py
gym_aloha/env.py
gym_aloha/utils.py
gym_aloha/tasks/sim.py
gym_aloha/tasks/sim_dummy.py
gym_aloha/tasks/sim_end_effector.py
gym_aloha_dummy-0.1.0.dist-info/METADATA
gym_aloha_dummy-0.1.0.dist-info/WHEEL
gym_aloha_dummy-0.1.0.dist-info/top_level.txt
gym_aloha_dummy-0.1.0.dist-info/RECORD
