Metadata-Version: 2.2
Name: gym-aloha-dummy
Version: 0.1.0
Summary: Add your description here
Requires-Python: >=3.11
Requires-Dist: dm-control>=1.0.27
Requires-Dist: gymnasium>=1.0.0
Requires-Dist: imageio[ffmpeg]>=2.37.0
Requires-Dist: ipython>=8.32.0
Requires-Dist: torch>=2.6.0
Requires-Dist: torchvision>=0.21.0
